MANIFEST.in
README.md
setup.py
src/date_detector/__init__.py
src/date_detector/__version__.py
src/date_detector/detector.py
src/date_detector.egg-info/PKG-INFO
src/date_detector.egg-info/SOURCES.txt
src/date_detector.egg-info/dependency_links.txt
src/date_detector.egg-info/entry_points.txt
src/date_detector.egg-info/namespace_packages.txt
src/date_detector.egg-info/not-zip-safe
src/date_detector.egg-info/requires.txt
src/date_detector.egg-info/top_level.txt
src/date_detector/dictionaries/en.txt
src/date_detector/dictionaries/he.txt