Metadata-Version: 1.1
Name: date-detector
Version: 1.0.2
Summary: A Python module for scanning text and extracting dates from it
Home-page: https://github.com/ishirav/date-detector
Author: Itai Shirav
Author-email: ishirav@gmail.com
License: BSD
Platform: UNKNOWN
Classifier: Intended Audience :: Developers
Classifier: Intended Audience :: System Administrators
Classifier: License :: OSI Approved :: BSD License
Classifier: Operating System :: OS Independent
Classifier: Programming Language :: Python
Classifier: Topic :: Software Development :: Libraries :: Python Modules
